[
  {
    "name": "_cfuvid",
    "value": "V_BOMlg5FyHSM4pnET9pRGBgKKBhatZ3PMFDVURoBDI-1778274740.892712-1.0.1.1-wlzx4buFXVoY_XAjeEs67899zFYjt8Q.OG1iUVEzhzc",
    "domain": ".cardmarket.com",
    "path": "/",
    "expires": -1,
    "size": 120,
    "httpOnly": true,
    "secure": true,
    "session": true,
    "sameSite": "None",
    "priority": "Medium",
    "sourceScheme": "Secure"
  },
  {
    "name": "__cf_bm",
    "value": ".Ij6IPXTS.7a7yNvNE_n_sML5s3BOMuJrpTdxIN4Zt8-1778274740.892712-1.0.1.1-3rQM6G00d1b1_3NrlKJBfgG1ObphF_neiC24NESZ0ofLkZY_6kAf7g1yz9MM5rZGHBU0n4MNHryAEUy449XZh7_Mbdooit2fGM5Gurv.gxqIMABVIkoHdBUf9xnkqzUU",
    "domain": ".cardmarket.com",
    "path": "/",
    "expires": 1778276541.008839,
    "size": 205,
    "httpOnly": true,
    "secure": true,
    "session": false,
    "priority": "Medium",
    "sourceScheme": "Secure"
  },
  {
    "name": "cookie_settings",
    "value": "preferences%3D0%2Cstatistics%3D0%2Cmarketing%3D0",
    "domain": "www.cardmarket.com",
    "path": "/",
    "expires": 1786213896.949454,
    "size": 63,
    "httpOnly": true,
    "secure": true,
    "session": false,
    "priority": "Medium",
    "sourceScheme": "Secure"
  },
  {
    "name": "PHPSESSID",
    "value": "ei48e7e6uqup8vvfj027s3r26b",
    "domain": "www.cardmarket.com",
    "path": "/",
    "expires": -1,
    "size": 35,
    "httpOnly": true,
    "secure": true,
    "session": true,
    "priority": "Medium",
    "sourceScheme": "Secure"
  }
]